__init__.py
asset_allocation/__init__.py
asset_allocation/kelly_portfolio.py
asset_allocation/tangent_portfolio.py
build/__init__.py
build/lib/__init__.py
build/lib/asset_allocation/__init__.py
build/lib/asset_allocation/kelly_portfolio.py
build/lib/asset_allocation/tangent_portfolio.py
build/lib/build/__init__.py
build/lib/build/lib/__init__.py
build/lib/build/lib/asset_allocation/__init__.py
build/lib/build/lib/asset_allocation/kelly_portfolio.py
build/lib/build/lib/asset_allocation/tangent_portfolio.py
build/lib/build/lib/build/__init__.py
build/lib/build/lib/build/lib/__init__.py
build/lib/build/lib/build/lib/asset_allocation/__init__.py
build/lib/build/lib/build/lib/asset_allocation/kelly_portfolio.py
build/lib/build/lib/build/lib/asset_allocation/tangent_portfolio.py
build/lib/build/lib/build/lib/date_handler/__init__.py
build/lib/build/lib/build/lib/date_handler/k_holiday.py
build/lib/build/lib/build/lib/date_handler/monthly_adjust.py
build/lib/build/lib/build/lib/date_handler/observe_period.py
build/lib/build/lib/build/lib/date_handler/rebalancing_period.py
build/lib/build/lib/build/lib/error_handler/__init__.py
build/lib/build/lib/build/lib/error_handler/type_tool.py
build/lib/build/lib/build/lib/general_tools/__init__.py
build/lib/build/lib/build/lib/general_tools/data_formatting.py
build/lib/build/lib/build/lib/stats/OLS.py
build/lib/build/lib/build/lib/stats/__init__.py
build/lib/build/lib/build/lib/stats/ewma_cov_mat.py
build/lib/build/lib/build/lib/stats/financial_signals.py
build/lib/build/lib/build/lib/stats/performance.py
build/lib/build/lib/date_handler/__init__.py
build/lib/build/lib/date_handler/k_holiday.py
build/lib/build/lib/date_handler/monthly_adjust.py
build/lib/build/lib/date_handler/observe_period.py
build/lib/build/lib/date_handler/rebalancing_period.py
build/lib/build/lib/error_handler/__init__.py
build/lib/build/lib/error_handler/type_tool.py
build/lib/build/lib/fpi_tool/__init__.py
finance_team_api-1.0.4.dist-info/METADATA
finance_team_api-1.0.4.dist-info/WHEEL
finance_team_api-1.0.4.dist-info/top_level.txt
finance_team_api-1.0.4.dist-info/RECORD
